enviame
