Metadata-Version: 2.1
Name: django-enviame
Version: 1.0.1
Summary: Django Enviame Integration
Home-page: https://gitlab.com/linets/ecommerce/oms/integrations/oms-enviame/
Author: Linets Development Team
Author-email: dteam@linets.cl
License: MIT
Platform: UNKNOWN
Requires-Python: >=3.7
